geometric_calibration/__init__.py
geometric_calibration/__main__.py
geometric_calibration/cli.py
geometric_calibration/geometric_calibration.py
geometric_calibration/reader.py
geometric_calibration/utils.py
geometric_calibration-0.2.0.dist-info/AUTHORS.rst
geometric_calibration-0.2.0.dist-info/LICENSE
geometric_calibration-0.2.0.dist-info/METADATA
geometric_calibration-0.2.0.dist-info/WHEEL
geometric_calibration-0.2.0.dist-info/entry_points.txt
geometric_calibration-0.2.0.dist-info/top_level.txt
geometric_calibration-0.2.0.dist-info/RECORD
