Metadata-Version: 2.1
Name: geometric-calibration
Version: 0.2.0
Summary: A utility to perform Geometric Calibration of a C-Arm Structure mounted on a robotic system
Home-page: https://github.com/mrossi93/geometric_calibration
Author: Matteo Rossi
Author-email: rossimatteo1993@gmail.com
License: MIT license
Keywords: geometric_calibration
Platform: UNKNOWN
Classifier: Development Status :: 2 - Pre-Alpha
Classifier: Intended Audience :: Developers
Classifier: License :: OSI Approved :: MIT License
Classifier: Natural Language :: English
Classifier: Programming Language :: Python :: 3
Classifier: Programming Language :: Python :: 3.6
Classifier: Programming Language :: Python :: 3.7
Classifier: Programming Language :: Python :: 3.8
Requires-Python: >=3.6
Requires-Dist: Click (>=7.0)
Requires-Dist: matplotlib
Requires-Dist: numpy
Requires-Dist: scipy
